asciitoart/__init__.py
asciitoart/__main__.py
asciitoart/version.py
asciitoart/fonts/ansi_regular.flf
asciitoart/fonts/ansi_shadow.flf
asciitoart/fonts/big.flf
asciitoart/fonts/big_money-ne.flf
asciitoart/fonts/big_money-nw.flf
asciitoart/fonts/big_money-se.flf
asciitoart/fonts/big_money-sw.flf
asciitoart/fonts/block.flf
asciitoart/fonts/blocky.flf
asciitoart/fonts/bloody.flf
asciitoart/fonts/broadway.flf
asciitoart/fonts/broadway_kb.flf
asciitoart/fonts/cricket.flf
asciitoart/fonts/doh.flf
asciitoart/fonts/doom.flf
asciitoart/fonts/dos_rebel.flf
asciitoart/fonts/electronic.flf
asciitoart/fonts/graffiti.flf
asciitoart/fonts/greek.flf
asciitoart/fonts/isometric1.flf
asciitoart/fonts/isometric2.flf
asciitoart/fonts/isometric3.flf
asciitoart/fonts/isometric4.flf
asciitoart/fonts/larry3d.flf
asciitoart/fonts/list.py
asciitoart/fonts/nipples.flf
asciitoart/fonts/poison.flf
asciitoart/fonts/red_phoenix.flf
asciitoart/fonts/slant.flf
asciitoart/fonts/slant_relief.flf
asciitoart/fonts/smisome1.flf
asciitoart/fonts/speed.flf
asciitoart/fonts/standard.flf
asciitoart/fonts/stop.flf
asciitoart/fonts/sub-zero.flf
asciitoart/fonts/swamp_land.flf
asciitoart/fonts/varsity.flf
asciitoart/fonts/otparse/__init__.py
asciitoart/fonts/otparse/dom/NodeFilter.py
asciitoart/fonts/otparse/dom/__init__.py
asciitoart/fonts/otparse/dom/domreg.py
asciitoart/fonts/otparse/dom/expatbuilder.py
asciitoart/fonts/otparse/dom/manifest.flc
asciitoart/fonts/otparse/dom/minicompat.py
asciitoart/fonts/otparse/dom/minidom.py
asciitoart/fonts/otparse/dom/mininode.py
asciitoart/fonts/otparse/dom/pulldom.py
asciitoart/fonts/otparse/dom/xmlbuilder.py
asciitoart/fonts/otparse/etree/ElementInclude.py
asciitoart/fonts/otparse/etree/ElementPath.py
asciitoart/fonts/otparse/etree/ElementTree.py
asciitoart/fonts/otparse/etree/__init__.py
asciitoart/fonts/otparse/etree/cElementTree.py
asciitoart/fonts/otparse/parsers/__init__.py
asciitoart/fonts/otparse/parsers/expat.py
asciitoart/fonts/otparse/sax/__init__.py
asciitoart-0.1.3.dist-info/METADATA
asciitoart-0.1.3.dist-info/WHEEL
asciitoart-0.1.3.dist-info/entry_points.txt
asciitoart-0.1.3.dist-info/top_level.txt
asciitoart-0.1.3.dist-info/RECORD
